partitialajax/__init__.py
partitialajax/admin.py
partitialajax/apps.py
partitialajax/exceptions.py
partitialajax/mixin.py
partitialajax/static/partitialajax/index.js
partitialajax/templates/partitialajax/partitial_include.html
partitialajax/templatetags/__init__.py
partitialajax/templatetags/partitialajax.py
partitialajax/tests/__init__.py
partitialajax/tests/test_html.py
partitialajax/tests/test_templatetag.py
django_partitialajax-0.2.2.dist-info/LICENSE
django_partitialajax-0.2.2.dist-info/METADATA
django_partitialajax-0.2.2.dist-info/WHEEL
django_partitialajax-0.2.2.dist-info/top_level.txt
django_partitialajax-0.2.2.dist-info/RECORD
